README.txt
setup.py
wikiup.cfg
Importing.egg-info/PKG-INFO
Importing.egg-info/SOURCES.txt
Importing.egg-info/dependency_links.txt
Importing.egg-info/namespace_packages.txt
Importing.egg-info/top_level.txt
ez_setup/README.txt
ez_setup/__init__.py
peak/__init__.py
peak/util/__init__.py
peak/util/imports.py