Metadata-Version: 1.0
Name: Importing
Version: 1.10
Summary: Import objects dynamically, lazily, "weakly", and more.
Home-page: http://peak.telecommunity.com/DevCenter/Importing
Author: Phillip J. Eby
Author-email: peak@eby-sarna.com
License: PSF or ZPL
Platform: UNKNOWN
